topsis_keshav_102303520/__init__.py
topsis_keshav_102303520/topsis.py
topsis_keshav_102303520-1.0.1.dist-info/METADATA
topsis_keshav_102303520-1.0.1.dist-info/WHEEL
topsis_keshav_102303520-1.0.1.dist-info/entry_points.txt
topsis_keshav_102303520-1.0.1.dist-info/top_level.txt
topsis_keshav_102303520-1.0.1.dist-info/RECORD
