Metadata-Version: 2.4
Name: topsis-keshav-102303520
Version: 1.0.1
Summary: TOPSIS decision making package
Author: Keshav Sharma
Requires-Python: >=3.7
Requires-Dist: pandas
Requires-Dist: numpy
Dynamic: author
Dynamic: description
Dynamic: description-content-type
Dynamic: requires-dist
Dynamic: requires-python
Dynamic: summary
